evds/__init__.py
evds-0.3.1.dist-info/LICENCE
evds-0.3.1.dist-info/METADATA
evds-0.3.1.dist-info/WHEEL
evds-0.3.1.dist-info/top_level.txt
evds-0.3.1.dist-info/RECORD
