Metadata-Version: 2.1
Name: evds
Version: 0.3.1
Summary: EVDS python wrapper
Home-page: https://github.com/fatihmete/evds
Author: Fatih Mete
Author-email: fatihmete@live.com
Classifier: Programming Language :: Python :: 3
Classifier: License :: OSI Approved :: MIT License
Classifier: Operating System :: OS Independent
Requires-Python: >=3.6
License-File: LICENCE
Requires-Dist: pandas
Requires-Dist: requests
Requires-Dist: urllib3
